[{
    "key": "group_61bc951d73494",
    "title": "Logotype grid",
    "fields": [
        {
            "key": "field_61bc9525fdb75",
            "label": "Add some brands",
            "name": "mod_logogrid",
            "type": "repeater",
            "instructions": "",
            "required": 0,
            "conditional_logic": 0,
            "wrapper": {
                "width": "",
                "class": "",
                "id": ""
            },
            "collapsed": "",
            "min": 2,
            "max": 99,
            "layout": "table",
            "button_label": "Add new logotype",
            "sub_fields": [
                {
                    "key": "field_61bc955cfdb77",
                    "label": "Image\/logotype",
                    "name": "mod_logogrid_image",
                    "type": "image",
                    "instructions": "",
                    "required": 1,
                    "conditional_logic": 0,
                    "wrapper": {
                        "width": "",
                        "class": "",
                        "id": ""
                    },
                    "return_format": "url",
                    "preview_size": "medium",
                    "library": "all",
                    "min_width": "",
                    "min_height": "",
                    "min_size": "",
                    "max_width": "",
                    "max_height": "",
                    "max_size": "",
                    "mime_types": "svg"
                },
                {
                    "key": "field_61bc9533fdb76",
                    "label": "Name",
                    "name": "mod_logogrid_name",
                    "type": "text",
                    "instructions": "",
                    "required": 1,
                    "conditional_logic": 0,
                    "wrapper": {
                        "width": "",
                        "class": "",
                        "id": ""
                    },
                    "default_value": "",
                    "placeholder": "",
                    "prepend": "",
                    "append": "",
                    "maxlength": ""
                },
                {
                    "key": "field_61bc958ffdb78",
                    "label": "Link",
                    "name": "mod_logogrid_link",
                    "type": "url",
                    "instructions": "",
                    "required": 0,
                    "conditional_logic": 0,
                    "wrapper": {
                        "width": "",
                        "class": "",
                        "id": ""
                    },
                    "default_value": "",
                    "placeholder": ""
                }
            ]
        }
    ],
    "location": [
        [
            {
                "param": "post_type",
                "operator": "==",
                "value": "mod-logogrid"
            }
        ],
        [
            {
                "param": "block",
                "operator": "==",
                "value": "acf\/logogrid"
            }
        ]
    ],
    "menu_order": 0,
    "position": "normal",
    "style": "default",
    "label_placement": "top",
    "instruction_placement": "label",
    "hide_on_screen": "",
    "active": true,
    "description": ""
}]
