[{
    "key": "group_5af4bcfa591d3",
    "title": "Customizer Header",
    "fields": [
        {
            "key": "field_5af4bd6cb2eaa",
            "label": "Site headers",
            "name": "customizer_headers",
            "type": "repeater",
            "instructions": "",
            "required": 0,
            "conditional_logic": 0,
            "wrapper": {
                "width": "",
                "class": "",
                "id": ""
            },
            "collapsed": "field_5af4cc022131b",
            "min": 1,
            "max": 0,
            "layout": "row",
            "button_label": "",
            "sub_fields": [
                {
                    "key": "field_5af4cc022131b",
                    "label": "Name",
                    "name": "name",
                    "type": "text",
                    "instructions": "",
                    "required": 1,
                    "conditional_logic": 0,
                    "wrapper": {
                        "width": "",
                        "class": "",
                        "id": ""
                    },
                    "default_value": "Header name",
                    "placeholder": "",
                    "prepend": "",
                    "append": "",
                    "maxlength": ""
                },
                {
                    "key": "field_5af58be1b2e22",
                    "label": "ID",
                    "name": "id",
                    "type": "text",
                    "instructions": "",
                    "required": 1,
                    "conditional_logic": 0,
                    "wrapper": {
                        "width": "",
                        "class": "",
                        "id": ""
                    },
                    "default_value": "unique-header-id",
                    "placeholder": "",
                    "prepend": "",
                    "append": "",
                    "maxlength": ""
                },
                {
                    "key": "field_5af58bf1b2e23",
                    "label": "Description",
                    "name": "description",
                    "type": "textarea",
                    "instructions": "",
                    "required": 0,
                    "conditional_logic": 0,
                    "wrapper": {
                        "width": "",
                        "class": "",
                        "id": ""
                    },
                    "default_value": "",
                    "new_lines": "",
                    "maxlength": "",
                    "placeholder": "",
                    "rows": ""
                },
                {
                    "key": "field_5af4cbfe2131a",
                    "label": "CSS Class (optional)",
                    "name": "css_class",
                    "type": "text",
                    "instructions": "",
                    "required": 0,
                    "conditional_logic": 0,
                    "wrapper": {
                        "width": "",
                        "class": "",
                        "id": ""
                    },
                    "default_value": "",
                    "placeholder": "",
                    "prepend": "",
                    "append": "",
                    "maxlength": ""
                }
            ]
        }
    ],
    "location": [
        [
            {
                "param": "options_page",
                "operator": "==",
                "value": "acf-options-cstomizer"
            }
        ]
    ],
    "menu_order": 0,
    "position": "normal",
    "style": "default",
    "label_placement": "top",
    "instruction_placement": "label",
    "hide_on_screen": "",
    "active": 1,
    "description": ""
}]
